CHANGELOG.txt
LICENSE.txt
MANIFEST.in
README.txt
first.py
sec1.py
setup.py
glowriya_calculator/__init__.py
glowriya_calculator.egg-info/PKG-INFO
glowriya_calculator.egg-info/SOURCES.txt
glowriya_calculator.egg-info/dependency_links.txt
glowriya_calculator.egg-info/top_level.txt